ml_models/__init__.py
ml_models/tree/__init__.py
ml_models/tree/impurity.py
ml_models/tree/tree.py
ml_models_augustin-0.1.2.dist-info/LICENSE
ml_models_augustin-0.1.2.dist-info/METADATA
ml_models_augustin-0.1.2.dist-info/WHEEL
ml_models_augustin-0.1.2.dist-info/top_level.txt
ml_models_augustin-0.1.2.dist-info/RECORD
